mockdata/__init__.py
mockdata/conftest.py
mockdata/functions.py
mockdata/mockdata.py
py_test_utility-0.0.2.dist-info/LICENSE
py_test_utility-0.0.2.dist-info/METADATA
py_test_utility-0.0.2.dist-info/WHEEL
py_test_utility-0.0.2.dist-info/top_level.txt
py_test_utility-0.0.2.dist-info/RECORD
