Metadata-Version: 2.1
Name: py-test-utility
Version: 0.0.2
Summary: useful package for pipelines testing and data mocking for new generation data warehouse
Home-page: https://github.com/bluefloyd00/py-test-utility
Author: Simone Fiorentini
Author-email: simone.fiorentini@gmail.com
License: UNKNOWN
Platform: UNKNOWN
Classifier: Programming Language :: Python :: 3
Classifier: License :: OSI Approved :: MIT License
Classifier: Operating System :: OS Independent
Requires-Python: >=3.6
